{
  "area": 12.512,
  "cell_footprint": "sky130_fd_sc_hdll__clkmux2",
  "cell_leakage_power": 2.791135,
  "leakage_power": [
    {
      "value": 3.19914,
      "when": "!A0&!A1&S"
    },
    {
      "value": 2.87035,
      "when": "!A0&!A1&!S"
    },
    {
      "value": 2.56713,
      "when": "!A0&A1&S"
    },
    {
      "value": 3.50207,
      "when": "!A0&A1&!S"
    },
    {
      "value": 3.82582,
      "when": "A0&!A1&S"
    },
    {
      "value": 2.2238,
      "when": "A0&!A1&!S"
    },
    {
      "value": 2.24466,
      "when": "A0&A1&S"
    },
    {
      "value": 1.89611,
      "when": "A0&A1&!S"
    }
  ],
  "pg_pin,VGND": {
    "pg_type": "primary_ground",
    "related_bias_pin": "VPB",
    "voltage_name": "VGND"
  },
  "pg_pin,VNB": {
    "pg_type": "nwell",
    "physical_connection": "device_layer",
    "voltage_name": "VNB"
  },
  "pg_pin,VPB": {
    "pg_type": "pwell",
    "physical_connection": "device_layer",
    "voltage_name": "VPB"
  },
  "pg_pin,VPWR": {
    "pg_type": "primary_power",
    "related_bias_pin": "VNB",
    "voltage_name": "VPWR"
  },
  "pin,A0": {
    "capacitance": 0.002164,
    "clock": "false",
    "direction": "input",
    "fall_capacitance": 0.002023,
    "internal_power": {
      "fall_power,power_inputs_1": {
        "index_1": [
          0.01,
          0.0230506,
          0.0531329,
          0.122474,
          0.282311,
          0.650743,
          1.5
        ],
        "values": [
          0.0036024,
          0.0035985,
          0.0035895,
          0.0035901,
          0.0035915,
          0.0035947,
          0.0036021
        ]
      },
      "rise_power,power_inputs_1": {
        "index_1": [
          0.01,
          0.0230506,
          0.0531329,
          0.122474,
          0.282311,
          0.650743,
          1.5
        ],
        "values": [
          -0.0024205,
          -0.0024424,
          -0.0024928,
          -0.0024965,
          -0.002505,
          -0.0025245,
          -0.0025694
        ]
      }
    },
    "max_transition": 1.5,
    "related_ground_pin": "VGND",
    "related_power_pin": "VPWR",
    "rise_capacitance": 0.002305
  },
  "pin,A1": {
    "capacitance": 0.002548,
    "clock": "false",
    "direction": "input",
    "fall_capacitance": 0.00239,
    "internal_power": {
      "fall_power,power_inputs_1": {
        "index_1": [
          0.01,
          0.0230506,
          0.0531329,
          0.122474,
          0.282311,
          0.650743,
          1.5
        ],
        "values": [
          0.0042732,
          0.0042744,
          0.004277,
          0.0042775,
          0.0042787,
          0.0042814,
          0.0042876
        ]
      },
      "rise_power,power_inputs_1": {
        "index_1": [
          0.01,
          0.0230506,
          0.0531329,
          0.122474,
          0.282311,
          0.650743,
          1.5
        ],
        "values": [
          -0.0036168,
          -0.0036264,
          -0.0036484,
          -0.0036495,
          -0.0036519,
          -0.0036574,
          -0.0036702
        ]
      }
    },
    "max_transition": 1.5,
    "related_ground_pin": "VGND",
    "related_power_pin": "VPWR",
    "rise_capacitance": 0.002706
  },
  "pin,S": {
    "capacitance": 0.004813,
    "clock": "false",
    "direction": "input",
    "fall_capacitance": 0.00458,
    "internal_power": {
      "fall_power,power_inputs_1": {
        "index_1": [
          0.01,
          0.0230506,
          0.0531329,
          0.122474,
          0.282311,
          0.650743,
          1.5
        ],
        "values": [
          0.0134174,
          0.0132741,
          0.0129436,
          0.0131941,
          0.0137717,
          0.015103,
          0.0181718
        ]
      },
      "rise_power,power_inputs_1": {
        "index_1": [
          0.01,
          0.0230506,
          0.0531329,
          0.122474,
          0.282311,
          0.650743,
          1.5
        ],
        "values": [
          -0.0023332,
          -0.0024603,
          -0.0027531,
          -0.0025194,
          -0.0019805,
          -0.0007385,
          0.0021244
        ]
      }
    },
    "max_transition": 1.5,
    "related_ground_pin": "VGND",
    "related_power_pin": "VPWR",
    "rise_capacitance": 0.005047
  },
  "pin,X": {
    "direction": "output",
    "function": "(A0&!S) | (A1&S)",
    "internal_power": [
      {
        "fall_power,power_outputs_1": {
          "index_1": [
            0.01,
            0.0230506,
            0.0531329,
            0.122474,
            0.282311,
            0.650743,
            1.5
          ],
          "index_2": [
            0.0005,
            0.0012526,
            0.003138,
            0.0078615,
            0.0196947,
            0.0493395,
            0.123606
          ],
          "values": [
            [
              0.008642,
              0.0078142,
              0.0059286,
              0.0002354,
              -0.0153478,
              -0.0556787,
              -0.1565225
            ],
            [
              0.0085836,
              0.007775,
              0.0058101,
              0.000277,
              -0.0154479,
              -0.0558012,
              -0.1569864
            ],
            [
              0.0084219,
              0.0077065,
              0.0056648,
              -3.75e-05,
              -0.0155019,
              -0.0559067,
              -0.1570894
            ],
            [
              0.0082666,
              0.007452,
              0.0054593,
              -0.0001081,
              -0.0157213,
              -0.0559995,
              -0.1569909
            ],
            [
              0.008322,
              0.0074823,
              0.0055023,
              -0.0001749,
              -0.0158449,
              -0.05606,
              -0.1570956
            ],
            [
              0.0102793,
              0.0091575,
              0.0065434,
              7.08e-05,
              -0.0153541,
              -0.0555966,
              -0.1566643
            ],
            [
              0.0130966,
              0.0118993,
              0.0090992,
              0.0024287,
              -0.0138447,
              -0.0540624,
              -0.1550946
            ]
          ]
        },
        "related_pin": "A0",
        "rise_power,power_outputs_1": {
          "index_1": [
            0.01,
            0.0230506,
            0.0531329,
            0.122474,
            0.282311,
            0.650743,
            1.5
          ],
          "index_2": [
            0.0005,
            0.0012526,
            0.003138,
            0.0078615,
            0.0196947,
            0.0493395,
            0.123606
          ],
          "values": [
            [
              0.0107327,
              0.0118378,
              0.0145162,
              0.021074,
              0.0372058,
              0.0771949,
              0.1759395
            ],
            [
              0.01076,
              0.0118723,
              0.0145415,
              0.021116,
              0.0372152,
              0.0772408,
              0.1758542
            ],
            [
              0.0107585,
              0.0118558,
              0.0145591,
              0.0211294,
              0.0372799,
              0.0775132,
              0.1764806
            ],
            [
              0.010668,
              0.0117593,
              0.0144529,
              0.0209766,
              0.0371345,
              0.0770621,
              0.1763673
            ],
            [
              0.0106641,
              0.0117452,
              0.0144006,
              0.0208847,
              0.0369214,
              0.0771434,
              0.1762784
            ],
            [
              0.0114604,
              0.0124581,
              0.0149498,
              0.0211486,
              0.0372481,
              0.0769546,
              0.1759287
            ],
            [
              0.013268,
              0.0142084,
              0.0166468,
              0.0229693,
              0.0388785,
              0.0784306,
              0.1773444
            ]
          ]
        }
      },
      {
        "fall_power,power_outputs_1": {
          "index_1": [
            0.01,
            0.0230506,
            0.0531329,
            0.122474,
            0.282311,
            0.650743,
            1.5
          ],
          "index_2": [
            0.0005,
            0.0012526,
            0.003138,
            0.0078615,
            0.0196947,
            0.0493395,
            0.123606
          ],
          "values": [
            [
              0.0087976,
              0.0080461,
              0.0062161,
              0.0004756,
              -0.0150118,
              -0.0550287,
              -0.1561282
            ],
            [
              0.0086802,
              0.0078806,
              0.0060109,
              0.0004046,
              -0.0151209,
              -0.0552555,
              -0.1562595
            ],
            [
              0.00853,
              0.0076619,
              0.0059395,
              0.0001672,
              -0.0152166,
              -0.0553619,
              -0.1564575
            ],
            [
              0.0082623,
              0.0074883,
              0.0055048,
              -7.58e-05,
              -0.0155263,
              -0.0556951,
              -0.1566571
            ],
            [
              0.0082683,
              0.0074281,
              0.0054865,
              -0.0001018,
              -0.015712,
              -0.0557999,
              -0.1567735
            ],
            [
              0.0101016,
              0.0089849,
              0.0063086,
              -9.5e-06,
              -0.0153395,
              -0.0554233,
              -0.1563796
            ],
            [
              0.0130471,
              0.0118523,
              0.0090387,
              0.0023815,
              -0.0138487,
              -0.0539519,
              -0.1548495
            ]
          ]
        },
        "related_pin": "A1",
        "rise_power,power_outputs_1": {
          "index_1": [
            0.01,
            0.0230506,
            0.0531329,
            0.122474,
            0.282311,
            0.650743,
            1.5
          ],
          "index_2": [
            0.0005,
            0.0012526,
            0.003138,
            0.0078615,
            0.0196947,
            0.0493395,
            0.123606
          ],
          "values": [
            [
              0.0120376,
              0.013115,
              0.0157118,
              0.0221282,
              0.0379575,
              0.0776659,
              0.1762932
            ],
            [
              0.0120548,
              0.0131287,
              0.0157154,
              0.0221199,
              0.038003,
              0.0780199,
              0.1768766
            ],
            [
              0.0119751,
              0.0130329,
              0.0156701,
              0.0220779,
              0.0379752,
              0.0780136,
              0.1771675
            ],
            [
              0.0118484,
              0.0129298,
              0.0155394,
              0.0219862,
              0.0378572,
              0.0775734,
              0.1771728
            ],
            [
              0.0118183,
              0.012874,
              0.0154686,
              0.0218736,
              0.0377382,
              0.0778304,
              0.1766898
            ],
            [
              0.0124731,
              0.0134628,
              0.0159935,
              0.0221832,
              0.0380986,
              0.0776455,
              0.1763429
            ],
            [
              0.0143347,
              0.015278,
              0.0177327,
              0.0240094,
              0.0398376,
              0.0792372,
              0.1778936
            ]
          ]
        }
      },
      {
        "fall_power,power_outputs_1": {
          "index_1": [
            0.01,
            0.0230506,
            0.0531329,
            0.122474,
            0.282311,
            0.650743,
            1.5
          ],
          "index_2": [
            0.0005,
            0.0012526,
            0.003138,
            0.0078615,
            0.0196947,
            0.0493395,
            0.123606
          ],
          "values": [
            [
              0.0115302,
              0.0107386,
              0.0089161,
              0.0031738,
              -0.0122931,
              -0.0524868,
              -0.1534643
            ],
            [
              0.0114745,
              0.010658,
              0.0087648,
              0.0031773,
              -0.0124379,
              -0.0526207,
              -0.1534608
            ],
            [
              0.0114955,
              0.0107013,
              0.0087913,
              0.0032496,
              -0.0123612,
              -0.0525441,
              -0.1533625
            ],
            [
              0.0110989,
              0.0102955,
              0.0084189,
              0.0029551,
              -0.0126999,
              -0.0528178,
              -0.1537241
            ],
            [
              0.0107556,
              0.0099701,
              0.0080779,
              0.0025464,
              -0.0130227,
              -0.0531258,
              -0.1540344
            ],
            [
              0.0128746,
              0.0118558,
              0.0093403,
              0.003026,
              -0.0131411,
              -0.0532601,
              -0.1541856
            ],
            [
              0.0133696,
              0.012313,
              0.0098345,
              0.0035315,
              -0.0124307,
              -0.0526351,
              -0.1538675
            ]
          ]
        },
        "related_pin": "S",
        "rise_power,power_outputs_1": {
          "index_1": [
            0.01,
            0.0230506,
            0.0531329,
            0.122474,
            0.282311,
            0.650743,
            1.5
          ],
          "index_2": [
            0.0005,
            0.0012526,
            0.003138,
            0.0078615,
            0.0196947,
            0.0493395,
            0.123606
          ],
          "values": [
            [
              0.0106016,
              0.0116881,
              0.0143858,
              0.0209654,
              0.0371051,
              0.0769694,
              0.1751507
            ],
            [
              0.0105644,
              0.0116449,
              0.0143418,
              0.0209348,
              0.0370279,
              0.0769988,
              0.1753351
            ],
            [
              0.0106994,
              0.011802,
              0.0144761,
              0.0210726,
              0.0371336,
              0.0771805,
              0.1756609
            ],
            [
              0.010454,
              0.011575,
              0.014259,
              0.0208196,
              0.0368999,
              0.0769045,
              0.1758077
            ],
            [
              0.0102211,
              0.0112957,
              0.0139955,
              0.0205261,
              0.0367662,
              0.0766473,
              0.1760422
            ],
            [
              0.0097458,
              0.0107797,
              0.0133808,
              0.0203807,
              0.0366739,
              0.0762746,
              0.1763142
            ],
            [
              0.0102832,
              0.0112922,
              0.0138983,
              0.0204073,
              0.03666,
              0.0771387,
              0.1753575
            ]
          ]
        }
      }
    ],
    "max_capacitance": 0.123606,
    "max_transition": 1.497661,
    "power_down_function": "(!VPWR + VGND)",
    "related_ground_pin": "VGND",
    "related_power_pin": "VPWR",
    "timing": [
      {
        "cell_fall,del_1_7_7": {
          "index_1": [
            0.01,
            0.0230506,
            0.0531329,
            0.122474,
            0.282311,
            0.650743,
            1.5
          ],
          "index_2": [
            0.0005,
            0.0012526,
            0.003138,
            0.0078615,
            0.0196947,
            0.0493395,
            0.123606
          ],
          "values": [
            [
              0.1282998,
              0.1353656,
              0.1499113,
              0.1781667,
              0.2334499,
              0.352682,
              0.6413568
            ],
            [
              0.1318681,
              0.1390153,
              0.1536786,
              0.1819798,
              0.2372258,
              0.356758,
              0.6455366
            ],
            [
              0.1408169,
              0.1478942,
              0.1624959,
              0.1907751,
              0.2461165,
              0.3656975,
              0.6544585
            ],
            [
              0.1635725,
              0.1706442,
              0.1851358,
              0.213499,
              0.2688327,
              0.3882079,
              0.6766368
            ],
            [
              0.2169634,
              0.2242046,
              0.2389312,
              0.2673133,
              0.3229255,
              0.4426405,
              0.731684
            ],
            [
              0.3037288,
              0.3122212,
              0.32986,
              0.3610476,
              0.418399,
              0.5405705,
              0.8297502
            ],
            [
              0.4435973,
              0.4536572,
              0.4738717,
              0.5106889,
              0.5744272,
              0.6990469,
              0.9901697
            ]
          ]
        },
        "cell_rise,del_1_7_7": {
          "index_1": [
            0.01,
            0.0230506,
            0.0531329,
            0.122474,
            0.282311,
            0.650743,
            1.5
          ],
          "index_2": [
            0.0005,
            0.0012526,
            0.003138,
            0.0078615,
            0.0196947,
            0.0493395,
            0.123606
          ],
          "values": [
            [
              0.1014753,
              0.108902,
              0.1245888,
              0.1576431,
              0.2330393,
              0.4171456,
              0.8767629
            ],
            [
              0.1050296,
              0.1124181,
              0.1281133,
              0.1611864,
              0.2364684,
              0.4209067,
              0.8801906
            ],
            [
              0.1129182,
              0.1203667,
              0.1360405,
              0.1690783,
              0.244629,
              0.4288142,
              0.889797
            ],
            [
              0.1314547,
              0.1387939,
              0.1543776,
              0.187368,
              0.2626902,
              0.4466211,
              0.9070571
            ],
            [
              0.1637574,
              0.1715392,
              0.1876357,
              0.2212306,
              0.2966239,
              0.4808545,
              0.9414073
            ],
            [
              0.1994309,
              0.2083626,
              0.2254395,
              0.2607418,
              0.3363874,
              0.5211677,
              0.9829403
            ],
            [
              0.2249836,
              0.2358194,
              0.2567238,
              0.2956009,
              0.3732782,
              0.5579824,
              1.018778
            ]
          ]
        },
        "fall_transition,del_1_7_7": {
          "index_1": [
            0.01,
            0.0230506,
            0.0531329,
            0.122474,
            0.282311,
            0.650743,
            1.5
          ],
          "index_2": [
            0.0005,
            0.0012526,
            0.003138,
            0.0078615,
            0.0196947,
            0.0493395,
            0.123606
          ],
          "values": [
            [
              0.0373498,
              0.0450002,
              0.0604452,
              0.0933919,
              0.1694414,
              0.3641577,
              0.8739225
            ],
            [
              0.0376081,
              0.0447999,
              0.0602166,
              0.0936655,
              0.169633,
              0.3636215,
              0.8827522
            ],
            [
              0.0380274,
              0.0449623,
              0.060482,
              0.093509,
              0.1691343,
              0.3637266,
              0.882558
            ],
            [
              0.0373168,
              0.044524,
              0.0596963,
              0.0934018,
              0.1696776,
              0.3643846,
              0.8790793
            ],
            [
              0.0405576,
              0.0479123,
              0.0630278,
              0.0950275,
              0.1706245,
              0.3647588,
              0.8791272
            ],
            [
              0.0527074,
              0.0600915,
              0.0748984,
              0.1068879,
              0.1809488,
              0.3693905,
              0.8847136
            ],
            [
              0.0702213,
              0.0792012,
              0.096893,
              0.1290345,
              0.19698,
              0.3782915,
              0.8763976
            ]
          ]
        },
        "related_pin": "A0",
        "rise_transition,del_1_7_7": {
          "index_1": [
            0.01,
            0.0230506,
            0.0531329,
            0.122474,
            0.282311,
            0.650743,
            1.5
          ],
          "index_2": [
            0.0005,
            0.0012526,
            0.003138,
            0.0078615,
            0.0196947,
            0.0493395,
            0.123606
          ],
          "values": [
            [
              0.0366748,
              0.0455325,
              0.0665207,
              0.118765,
              0.2559148,
              0.6084234,
              1.4946786
            ],
            [
              0.0366652,
              0.0454731,
              0.0666299,
              0.1188303,
              0.2558453,
              0.6092243,
              1.4968304
            ],
            [
              0.0366628,
              0.0455224,
              0.0664704,
              0.1188442,
              0.2558407,
              0.6087841,
              1.4970993
            ],
            [
              0.0362377,
              0.045352,
              0.0664736,
              0.1189894,
              0.2559946,
              0.607903,
              1.4941492
            ],
            [
              0.0403915,
              0.0492752,
              0.0698128,
              0.1211151,
              0.2563946,
              0.6078795,
              1.4950257
            ],
            [
              0.0484376,
              0.0580561,
              0.0782003,
              0.1267769,
              0.2596737,
              0.6081385,
              1.4950149
            ],
            [
              0.0620261,
              0.0724866,
              0.0929943,
              0.1397222,
              0.264595,
              0.6098457,
              1.492651
            ]
          ]
        },
        "timing_sense": "positive_unate",
        "timing_type": "combinational"
      },
      {
        "cell_fall,del_1_7_7": {
          "index_1": [
            0.01,
            0.0230506,
            0.0531329,
            0.122474,
            0.282311,
            0.650743,
            1.5
          ],
          "index_2": [
            0.0005,
            0.0012526,
            0.003138,
            0.0078615,
            0.0196947,
            0.0493395,
            0.123606
          ],
          "values": [
            [
              0.1374883,
              0.1447406,
              0.1594799,
              0.1882273,
              0.2439065,
              0.3637504,
              0.6530218
            ],
            [
              0.1408576,
              0.1480287,
              0.1628109,
              0.1913334,
              0.2470498,
              0.3670365,
              0.6560364
            ],
            [
              0.1493247,
              0.1564964,
              0.1713144,
              0.2000249,
              0.255666,
              0.3755715,
              0.6648083
            ],
            [
              0.1716397,
              0.1787541,
              0.1934939,
              0.2221179,
              0.2781005,
              0.3979135,
              0.6868185
            ],
            [
              0.2247581,
              0.2320414,
              0.2468349,
              0.275608,
              0.3314658,
              0.4513577,
              0.7404017
            ],
            [
              0.3137004,
              0.3222465,
              0.3392719,
              0.3706869,
              0.429082,
              0.5507267,
              0.8402736
            ],
            [
              0.4549879,
              0.4652006,
              0.4854195,
              0.5222451,
              0.586136,
              0.7112872,
              1.0025191
            ]
          ]
        },
        "cell_rise,del_1_7_7": {
          "index_1": [
            0.01,
            0.0230506,
            0.0531329,
            0.122474,
            0.282311,
            0.650743,
            1.5
          ],
          "index_2": [
            0.0005,
            0.0012526,
            0.003138,
            0.0078615,
            0.0196947,
            0.0493395,
            0.123606
          ],
          "values": [
            [
              0.102597,
              0.1098566,
              0.1251218,
              0.1572716,
              0.2316137,
              0.4154586,
              0.8737754
            ],
            [
              0.1060727,
              0.1133017,
              0.1285261,
              0.1608158,
              0.2349802,
              0.4182992,
              0.8777615
            ],
            [
              0.113766,
              0.1210188,
              0.1362821,
              0.1685517,
              0.2429109,
              0.4269625,
              0.8867774
            ],
            [
              0.1324135,
              0.1395729,
              0.1548054,
              0.187156,
              0.2613509,
              0.4447799,
              0.9034897
            ],
            [
              0.1645148,
              0.1721172,
              0.1879905,
              0.2211266,
              0.2957368,
              0.4789339,
              0.9390347
            ],
            [
              0.1998061,
              0.2086377,
              0.2258734,
              0.2604501,
              0.3355178,
              0.519639,
              0.9811206
            ],
            [
              0.2252179,
              0.2360276,
              0.2575178,
              0.2955572,
              0.3727662,
              0.5569217,
              1.0167651
            ]
          ]
        },
        "fall_transition,del_1_7_7": {
          "index_1": [
            0.01,
            0.0230506,
            0.0531329,
            0.122474,
            0.282311,
            0.650743,
            1.5
          ],
          "index_2": [
            0.0005,
            0.0012526,
            0.003138,
            0.0078615,
            0.0196947,
            0.0493395,
            0.123606
          ],
          "values": [
            [
              0.0378125,
              0.0451458,
              0.0608938,
              0.0938956,
              0.170173,
              0.3645293,
              0.8785509
            ],
            [
              0.0382656,
              0.0455073,
              0.0604649,
              0.0939791,
              0.1703394,
              0.3645435,
              0.8745048
            ],
            [
              0.0383819,
              0.045462,
              0.0609634,
              0.0939211,
              0.1697741,
              0.3639506,
              0.8805697
            ],
            [
              0.0379286,
              0.0454778,
              0.0605027,
              0.0937988,
              0.169867,
              0.3647739,
              0.8745715
            ],
            [
              0.0405614,
              0.0476234,
              0.0626985,
              0.095406,
              0.1707512,
              0.3649434,
              0.873582
            ],
            [
              0.053102,
              0.059694,
              0.0756074,
              0.1067964,
              0.1806522,
              0.3693381,
              0.8767416
            ],
            [
              0.0697832,
              0.0788418,
              0.096402,
              0.1283301,
              0.1965173,
              0.3791354,
              0.8792112
            ]
          ]
        },
        "related_pin": "A1",
        "rise_transition,del_1_7_7": {
          "index_1": [
            0.01,
            0.0230506,
            0.0531329,
            0.122474,
            0.282311,
            0.650743,
            1.5
          ],
          "index_2": [
            0.0005,
            0.0012526,
            0.003138,
            0.0078615,
            0.0196947,
            0.0493395,
            0.123606
          ],
          "values": [
            [
              0.0364915,
              0.0455795,
              0.0662361,
              0.118532,
              0.2558115,
              0.6081931,
              1.4962671
            ],
            [
              0.0364556,
              0.0454089,
              0.066336,
              0.1185423,
              0.2557866,
              0.6081933,
              1.4949137
            ],
            [
              0.036644,
              0.0452978,
              0.0662273,
              0.1186042,
              0.2550161,
              0.609592,
              1.4966359
            ],
            [
              0.0362102,
              0.0452079,
              0.0661278,
              0.1186745,
              0.2556352,
              0.6088026,
              1.4921298
            ],
            [
              0.040511,
              0.0493118,
              0.0694964,
              0.1208987,
              0.2562491,
              0.6082553,
              1.4963334
            ],
            [
              0.048724,
              0.0574347,
              0.0775866,
              0.1262262,
              0.2595449,
              0.6097142,
              1.494082
            ],
            [
              0.0623104,
              0.072938,
              0.0937931,
              0.1398393,
              0.2649199,
              0.6103802,
              1.4933828
            ]
          ]
        },
        "timing_sense": "positive_unate",
        "timing_type": "combinational"
      },
      {
        "cell_fall,del_1_7_7": {
          "index_1": [
            0.01,
            0.0230506,
            0.0531329,
            0.122474,
            0.282311,
            0.650743,
            1.5
          ],
          "index_2": [
            0.0005,
            0.0012526,
            0.003138,
            0.0078615,
            0.0196947,
            0.0493395,
            0.123606
          ],
          "values": [
            [
              0.149358,
              0.1565143,
              0.1710489,
              0.1992426,
              0.2543371,
              0.3734647,
              0.6619365
            ],
            [
              0.1536337,
              0.1607175,
              0.1753298,
              0.2035756,
              0.258641,
              0.3777128,
              0.6658523
            ],
            [
              0.1634295,
              0.1705091,
              0.1851156,
              0.2133763,
              0.2684757,
              0.3875716,
              0.6755583
            ],
            [
              0.1838887,
              0.190956,
              0.205534,
              0.2336994,
              0.2888722,
              0.408137,
              0.6964718
            ],
            [
              0.2271561,
              0.2344066,
              0.2492229,
              0.2777455,
              0.3331967,
              0.4526907,
              0.741093
            ],
            [
              0.299636,
              0.3076957,
              0.3241255,
              0.3553194,
              0.4143873,
              0.5364628,
              0.8258881
            ],
            [
              0.4218116,
              0.4309967,
              0.4502052,
              0.4858563,
              0.5506569,
              0.6771018,
              0.9673392
            ]
          ]
        },
        "cell_rise,del_1_7_7": {
          "index_1": [
            0.01,
            0.0230506,
            0.0531329,
            0.122474,
            0.282311,
            0.650743,
            1.5
          ],
          "index_2": [
            0.0005,
            0.0012526,
            0.003138,
            0.0078615,
            0.0196947,
            0.0493395,
            0.123606
          ],
          "values": [
            [
              0.1084557,
              0.1157618,
              0.1310152,
              0.163215,
              0.2370566,
              0.4199477,
              0.8784927
            ],
            [
              0.1115149,
              0.118791,
              0.1340538,
              0.1662672,
              0.2400838,
              0.4229211,
              0.8810033
            ],
            [
              0.1182709,
              0.1255315,
              0.1408091,
              0.1730396,
              0.2468508,
              0.4301149,
              0.8878976
            ],
            [
              0.1336545,
              0.140818,
              0.1560588,
              0.1883598,
              0.2623351,
              0.445665,
              0.9036257
            ],
            [
              0.16103,
              0.1687313,
              0.1847192,
              0.21778,
              0.2923911,
              0.4755871,
              0.9346083
            ],
            [
              0.1953646,
              0.2038942,
              0.2214939,
              0.2561429,
              0.3318591,
              0.5154129,
              0.9747848
            ],
            [
              0.2227483,
              0.2330058,
              0.2536513,
              0.2919693,
              0.369612,
              0.5537713,
              1.0134045
            ]
          ]
        },
        "fall_transition,del_1_7_7": {
          "index_1": [
            0.01,
            0.0230506,
            0.0531329,
            0.122474,
            0.282311,
            0.650743,
            1.5
          ],
          "index_2": [
            0.0005,
            0.0012526,
            0.003138,
            0.0078615,
            0.0196947,
            0.0493395,
            0.123606
          ],
          "values": [
            [
              0.0375742,
              0.0446325,
              0.0603345,
              0.0937003,
              0.1696158,
              0.3641228,
              0.8739503
            ],
            [
              0.0377746,
              0.0448768,
              0.0604614,
              0.0936458,
              0.1696293,
              0.3640673,
              0.8793447
            ],
            [
              0.0377944,
              0.044915,
              0.060463,
              0.0936498,
              0.1696263,
              0.3640619,
              0.8785663
            ],
            [
              0.0377555,
              0.0449122,
              0.0605259,
              0.0938433,
              0.1695201,
              0.3642671,
              0.8761614
            ],
            [
              0.0397878,
              0.0468985,
              0.0625234,
              0.0946783,
              0.1701084,
              0.364382,
              0.8755356
            ],
            [
              0.0473585,
              0.0546121,
              0.0711831,
              0.1043879,
              0.1803886,
              0.369325,
              0.8833617
            ],
            [
              0.060821,
              0.0703052,
              0.0880023,
              0.1228479,
              0.1972769,
              0.3804792,
              0.8761007
            ]
          ]
        },
        "related_pin": "S",
        "rise_transition,del_1_7_7": {
          "index_1": [
            0.01,
            0.0230506,
            0.0531329,
            0.122474,
            0.282311,
            0.650743,
            1.5
          ],
          "index_2": [
            0.0005,
            0.0012526,
            0.003138,
            0.0078615,
            0.0196947,
            0.0493395,
            0.123606
          ],
          "values": [
            [
              0.0364873,
              0.0454368,
              0.0663363,
              0.1184761,
              0.2557924,
              0.6082034,
              1.4967219
            ],
            [
              0.0364651,
              0.0452579,
              0.0661424,
              0.1184418,
              0.2552612,
              0.6085867,
              1.4936572
            ],
            [
              0.0364744,
              0.0452013,
              0.0661603,
              0.1184871,
              0.2554694,
              0.6092654,
              1.4959644
            ],
            [
              0.0364167,
              0.0451936,
              0.0662063,
              0.1187638,
              0.2555573,
              0.6091683,
              1.4936895
            ],
            [
              0.039872,
              0.0485526,
              0.0692813,
              0.1205595,
              0.2564325,
              0.6076661,
              1.4920478
            ],
            [
              0.0461153,
              0.05604,
              0.0761821,
              0.1254551,
              0.2595693,
              0.6082526,
              1.4958295
            ],
            [
              0.0581118,
              0.0685079,
              0.0893015,
              0.1372443,
              0.2638902,
              0.6099768,
              1.492547
            ]
          ]
        },
        "timing_sense": "positive_unate",
        "timing_type": "combinational"
      },
      {
        "cell_fall,del_1_7_7": {
          "index_1": [
            0.01,
            0.0230506,
            0.0531329,
            0.122474,
            0.282311,
            0.650743,
            1.5
          ],
          "index_2": [
            0.0005,
            0.0012526,
            0.003138,
            0.0078615,
            0.0196947,
            0.0493395,
            0.123606
          ],
          "values": [
            [
              0.1646298,
              0.1717818,
              0.1864429,
              0.2148981,
              0.2705637,
              0.3903699,
              0.6791655
            ],
            [
              0.1688012,
              0.175945,
              0.1906803,
              0.2192314,
              0.2750603,
              0.3947775,
              0.6837051
            ],
            [
              0.1773761,
              0.1845185,
              0.199211,
              0.2277955,
              0.2836915,
              0.4034659,
              0.6923479
            ],
            [
              0.1888622,
              0.1960091,
              0.2107811,
              0.2394703,
              0.2952724,
              0.4150834,
              0.703787
            ],
            [
              0.2008569,
              0.2079682,
              0.2226375,
              0.2509937,
              0.306782,
              0.4267557,
              0.7160857
            ],
            [
              0.208461,
              0.2155699,
              0.2303412,
              0.2588453,
              0.3144868,
              0.4340954,
              0.722287
            ],
            [
              0.1950908,
              0.2022402,
              0.2170252,
              0.2457708,
              0.3016208,
              0.4212779,
              0.7095299
            ]
          ]
        },
        "cell_rise,del_1_7_7": {
          "index_1": [
            0.01,
            0.0230506,
            0.0531329,
            0.122474,
            0.282311,
            0.650743,
            1.5
          ],
          "index_2": [
            0.0005,
            0.0012526,
            0.003138,
            0.0078615,
            0.0196947,
            0.0493395,
            0.123606
          ],
          "values": [
            [
              0.1473544,
              0.1547692,
              0.1704971,
              0.2035858,
              0.278773,
              0.463406,
              0.9218253
            ],
            [
              0.1517628,
              0.1591329,
              0.1748679,
              0.2079612,
              0.2831606,
              0.4678472,
              0.926444
            ],
            [
              0.1629079,
              0.1702829,
              0.1860238,
              0.2191197,
              0.2943153,
              0.4789845,
              0.937457
            ],
            [
              0.1871293,
              0.1945372,
              0.2102406,
              0.2433491,
              0.3186944,
              0.5039184,
              0.9628079
            ],
            [
              0.2262382,
              0.2335895,
              0.2492639,
              0.2824291,
              0.3579156,
              0.5421046,
              1.0030297
            ],
            [
              0.2894579,
              0.2966986,
              0.3126913,
              0.3457771,
              0.4208167,
              0.6045842,
              1.0665584
            ],
            [
              0.3998282,
              0.4073224,
              0.4231615,
              0.4563241,
              0.5315724,
              0.7156993,
              1.1752856
            ]
          ]
        },
        "fall_transition,del_1_7_7": {
          "index_1": [
            0.01,
            0.0230506,
            0.0531329,
            0.122474,
            0.282311,
            0.650743,
            1.5
          ],
          "index_2": [
            0.0005,
            0.0012526,
            0.003138,
            0.0078615,
            0.0196947,
            0.0493395,
            0.123606
          ],
          "values": [
            [
              0.0379333,
              0.0449968,
              0.0606904,
              0.0936288,
              0.169441,
              0.3643128,
              0.8750185
            ],
            [
              0.0381662,
              0.045132,
              0.0611597,
              0.0942222,
              0.1698414,
              0.3648925,
              0.8773411
            ],
            [
              0.0377272,
              0.0454977,
              0.0605072,
              0.0943417,
              0.1696971,
              0.3648558,
              0.8813879
            ],
            [
              0.037719,
              0.0454536,
              0.060474,
              0.093756,
              0.1701815,
              0.3646483,
              0.8792939
            ],
            [
              0.0378728,
              0.0450779,
              0.0597068,
              0.0934307,
              0.1698299,
              0.3643432,
              0.8796443
            ],
            [
              0.0377162,
              0.0453373,
              0.0603452,
              0.0931559,
              0.169672,
              0.3614883,
              0.8729473
            ],
            [
              0.0383153,
              0.0459422,
              0.0607374,
              0.0941367,
              0.1703014,
              0.3647032,
              0.8762604
            ]
          ]
        },
        "related_pin": "S",
        "rise_transition,del_1_7_7": {
          "index_1": [
            0.01,
            0.0230506,
            0.0531329,
            0.122474,
            0.282311,
            0.650743,
            1.5
          ],
          "index_2": [
            0.0005,
            0.0012526,
            0.003138,
            0.0078615,
            0.0196947,
            0.0493395,
            0.123606
          ],
          "values": [
            [
              0.036608,
              0.0455452,
              0.0665401,
              0.1186071,
              0.2555936,
              0.6091733,
              1.4953971
            ],
            [
              0.0365658,
              0.0455752,
              0.0665336,
              0.1185847,
              0.2556618,
              0.6092763,
              1.4957253
            ],
            [
              0.0365674,
              0.0456337,
              0.0665903,
              0.1188384,
              0.2556847,
              0.6092709,
              1.4954858
            ],
            [
              0.0367495,
              0.0456245,
              0.0665955,
              0.1189807,
              0.2559772,
              0.607814,
              1.4943498
            ],
            [
              0.0364354,
              0.0453947,
              0.0665064,
              0.1187081,
              0.2560551,
              0.6090303,
              1.4968153
            ],
            [
              0.0369316,
              0.0458083,
              0.066863,
              0.1191086,
              0.2551919,
              0.60641,
              1.4976613
            ],
            [
              0.0375322,
              0.046495,
              0.0673959,
              0.1195314,
              0.2564643,
              0.6080742,
              1.4888258
            ]
          ]
        },
        "timing_sense": "negative_unate",
        "timing_type": "combinational"
      }
    ]
  }
}