{
  "area": 11.2608,
  "cell_footprint": "and4b",
  "cell_leakage_power": 0.0,
  "pg_pin VGND": {
    "pg_type": "primary_ground",
    "related_bias_pin": "VNB",
    "voltage_name": "VGND"
  },
  "pg_pin VNB": {
    "pg_type": "pwell",
    "voltage_name": "VNB"
  },
  "pg_pin VPB": {
    "pg_type": "nwell",
    "voltage_name": "VPB"
  },
  "pg_pin VPWR": {
    "pg_type": "primary_power",
    "related_bias_pin": "VPB",
    "voltage_name": "VPWR"
  },
  "pin A_N": {
    "capacitance": 0.001431,
    "clock": "false",
    "direction": "input",
    "fall_capacitance": 0.001344,
    "internal_power": {
      "fall_power power_inputs_1": {
        "index_1": [
          0.01,
          0.0230506,
          0.0531329,
          0.122474,
          0.282311,
          0.650743,
          1.5
        ],
        "values": [
          0.006702,
          0.0066208,
          0.0064337,
          0.0064023,
          0.00633,
          0.0061633,
          0.005779
        ]
      },
      "rise_power power_inputs_1": {
        "index_1": [
          0.01,
          0.0230506,
          0.0531329,
          0.122474,
          0.282311,
          0.650743,
          1.5
        ],
        "values": [
          0.0021485,
          0.0020817,
          0.0019276,
          0.0019075,
          0.0018612,
          0.0017545,
          0.0015086
        ]
      }
    },
    "max_transition": 1.5,
    "related_ground_pin": "VGND",
    "related_power_pin": "VPWR",
    "rise_capacitance": 0.001517
  },
  "pin B": {
    "capacitance": 0.001519,
    "clock": "false",
    "direction": "input",
    "fall_capacitance": 0.001491,
    "internal_power": {
      "fall_power power_inputs_1": {
        "index_1": [
          0.01,
          0.0230506,
          0.0531329,
          0.122474,
          0.282311,
          0.650743,
          1.5
        ],
        "values": [
          0.0026785,
          0.0026607,
          0.0026197,
          0.0026212,
          0.0026247,
          0.0026328,
          0.0026514
        ]
      },
      "rise_power power_inputs_1": {
        "index_1": [
          0.01,
          0.0230506,
          0.0531329,
          0.122474,
          0.282311,
          0.650743,
          1.5
        ],
        "values": [
          -0.0023025,
          -0.0023096,
          -0.0023258,
          -0.0023197,
          -0.0023055,
          -0.0022729,
          -0.0021977
        ]
      }
    },
    "max_transition": 1.5,
    "related_ground_pin": "VGND",
    "related_power_pin": "VPWR",
    "rise_capacitance": 0.001548
  },
  "pin C": {
    "capacitance": 0.001478,
    "clock": "false",
    "direction": "input",
    "fall_capacitance": 0.001453,
    "internal_power": {
      "fall_power power_inputs_1": {
        "index_1": [
          0.01,
          0.0230506,
          0.0531329,
          0.122474,
          0.282311,
          0.650743,
          1.5
        ],
        "values": [
          0.0018109,
          0.0018131,
          0.0018182,
          0.001817,
          0.0018143,
          0.0018081,
          0.0017937
        ]
      },
      "rise_power power_inputs_1": {
        "index_1": [
          0.01,
          0.0230506,
          0.0531329,
          0.122474,
          0.282311,
          0.650743,
          1.5
        ],
        "values": [
          -0.0018085,
          -0.0018006,
          -0.0017824,
          -0.0017833,
          -0.0017855,
          -0.0017903,
          -0.0018016
        ]
      }
    },
    "max_transition": 1.5,
    "related_ground_pin": "VGND",
    "related_power_pin": "VPWR",
    "rise_capacitance": 0.001504
  },
  "pin D": {
    "capacitance": 0.001472,
    "clock": "false",
    "direction": "input",
    "fall_capacitance": 0.001419,
    "internal_power": {
      "fall_power power_inputs_1": {
        "index_1": [
          0.01,
          0.0230506,
          0.0531329,
          0.122474,
          0.282311,
          0.650743,
          1.5
        ],
        "values": [
          0.0021874,
          0.0021888,
          0.0021921,
          0.0021961,
          0.0022052,
          0.0022262,
          0.0022746
        ]
      },
      "rise_power power_inputs_1": {
        "index_1": [
          0.01,
          0.0230506,
          0.0531329,
          0.122474,
          0.282311,
          0.650743,
          1.5
        ],
        "values": [
          -0.0022296,
          -0.002217,
          -0.0021878,
          -0.0021894,
          -0.0021932,
          -0.0022018,
          -0.0022218
        ]
      }
    },
    "max_transition": 1.5,
    "related_ground_pin": "VGND",
    "related_power_pin": "VPWR",
    "rise_capacitance": 0.001524
  },
  "pin X": {
    "direction": "output",
    "function": "(!A_N&B&C&D)",
    "internal_power": [
      {
        "fall_power power_outputs_1": {
          "index_1": [
            0.01,
            0.0230506,
            0.0531329,
            0.122474,
            0.282311,
            0.650743,
            1.5
          ],
          "index_2": [
            0.0005,
            0.001165835,
            0.002718342,
            0.006338276,
            0.01477877,
            0.03445921,
            0.0803475
          ],
          "values": [
            [
              0.0094476,
              0.0086623,
              0.0067173,
              0.0017008,
              -0.0108002,
              -0.0409406,
              -0.111868
            ],
            [
              0.009423,
              0.008625,
              0.0066356,
              0.00165,
              -0.010841,
              -0.0409687,
              -0.1118823
            ],
            [
              0.0093305,
              0.0085598,
              0.0065832,
              0.0015853,
              -0.0109094,
              -0.041034,
              -0.1119587
            ],
            [
              0.0092186,
              0.0084049,
              0.0064518,
              0.0014403,
              -0.0109945,
              -0.0411537,
              -0.112056
            ],
            [
              0.0090447,
              0.008291,
              0.0063359,
              0.0013469,
              -0.0111192,
              -0.0412686,
              -0.1121156
            ],
            [
              0.008973,
              0.0081126,
              0.0061735,
              0.0010485,
              -0.0114191,
              -0.0415181,
              -0.1123225
            ],
            [
              0.0087489,
              0.0079581,
              0.0059644,
              0.0009429,
              -0.011797,
              -0.0417689,
              -0.1124624
            ]
          ]
        },
        "related_pin": "C",
        "rise_power power_outputs_1": {
          "index_1": [
            0.01,
            0.0230506,
            0.0531329,
            0.122474,
            0.282311,
            0.650743,
            1.5
          ],
          "index_2": [
            0.0005,
            0.001165835,
            0.002718342,
            0.006338276,
            0.01477877,
            0.03445921,
            0.0803475
          ],
          "values": [
            [
              0.0119718,
              0.0131422,
              0.0157589,
              0.0214731,
              0.0344039,
              0.0645648,
              0.1349841
            ],
            [
              0.011958,
              0.0131052,
              0.0156267,
              0.021354,
              0.0343469,
              0.0648177,
              0.1330002
            ],
            [
              0.0119188,
              0.0130821,
              0.0156129,
              0.0214349,
              0.0343155,
              0.0649046,
              0.1338639
            ],
            [
              0.0118569,
              0.0131307,
              0.0156519,
              0.0212977,
              0.0342948,
              0.0645277,
              0.1341841
            ],
            [
              0.0118127,
              0.0129817,
              0.0155241,
              0.0212515,
              0.0343256,
              0.0645495,
              0.1339613
            ],
            [
              0.0116972,
              0.0128489,
              0.0153457,
              0.0210728,
              0.0342483,
              0.0644237,
              0.134332
            ],
            [
              0.0120439,
              0.0131642,
              0.0156544,
              0.0211968,
              0.0343122,
              0.0642996,
              0.1341244
            ]
          ]
        },
        "when": "(!A_N&B&D)"
      },
      {
        "fall_power power_outputs_1": {
          "index_1": [
            0.01,
            0.0230506,
            0.0531329,
            0.122474,
            0.282311,
            0.650743,
            1.5
          ],
          "index_2": [
            0.0005,
            0.001165835,
            0.002718342,
            0.006338276,
            0.01477877,
            0.03445921,
            0.0803475
          ],
          "values": [
            [
              0.0105007,
              0.0096832,
              0.007677,
              0.0025821,
              -0.0100369,
              -0.0403339,
              -0.1113729
            ],
            [
              0.0104369,
              0.0095863,
              0.007594,
              0.00254,
              -0.010112,
              -0.0403782,
              -0.1112427
            ],
            [
              0.0103359,
              0.0095325,
              0.0075367,
              0.0024127,
              -0.010186,
              -0.0403812,
              -0.1114313
            ],
            [
              0.0102068,
              0.0093804,
              0.0073895,
              0.0023025,
              -0.0103143,
              -0.0405479,
              -0.1115022
            ],
            [
              0.0100471,
              0.0092104,
              0.00722,
              0.0021375,
              -0.0104127,
              -0.0406283,
              -0.1115052
            ],
            [
              0.0098062,
              0.0089716,
              0.0069722,
              0.0019266,
              -0.0107264,
              -0.0408319,
              -0.1118185
            ],
            [
              0.009591,
              0.0087516,
              0.0067595,
              0.0016892,
              -0.010821,
              -0.040982,
              -0.1119016
            ]
          ]
        },
        "related_pin": "D",
        "rise_power power_outputs_1": {
          "index_1": [
            0.01,
            0.0230506,
            0.0531329,
            0.122474,
            0.282311,
            0.650743,
            1.5
          ],
          "index_2": [
            0.0005,
            0.001165835,
            0.002718342,
            0.006338276,
            0.01477877,
            0.03445921,
            0.0803475
          ],
          "values": [
            [
              0.0124516,
              0.0135771,
              0.0161774,
              0.0219002,
              0.0348827,
              0.0650526,
              0.1336068
            ],
            [
              0.0124192,
              0.0135372,
              0.0160914,
              0.0219187,
              0.0347963,
              0.064895,
              0.1355089
            ],
            [
              0.0123467,
              0.0135873,
              0.0160342,
              0.0217825,
              0.0348468,
              0.0649706,
              0.1335035
            ],
            [
              0.0122955,
              0.0134679,
              0.0160467,
              0.021801,
              0.0347526,
              0.0648607,
              0.135202
            ],
            [
              0.0121941,
              0.0134129,
              0.0158233,
              0.0215358,
              0.0346099,
              0.0648437,
              0.1335925
            ],
            [
              0.0120462,
              0.0131658,
              0.0156489,
              0.0214494,
              0.0346048,
              0.0647924,
              0.1339281
            ],
            [
              0.0123711,
              0.0134172,
              0.0159087,
              0.0213304,
              0.0345294,
              0.0645466,
              0.1345859
            ]
          ]
        },
        "when": "(!A_N&B&C)"
      },
      {
        "fall_power power_outputs_1": {
          "index_1": [
            0.01,
            0.0230506,
            0.0531329,
            0.122474,
            0.282311,
            0.650743,
            1.5
          ],
          "index_2": [
            0.0005,
            0.001165835,
            0.002718342,
            0.006338276,
            0.01477877,
            0.03445921,
            0.0803475
          ],
          "values": [
            [
              0.0075497,
              0.0067549,
              0.0048765,
              -7.97e-05,
              -0.0125863,
              -0.0428441,
              -0.1137841
            ],
            [
              0.0075894,
              0.0068156,
              0.0049034,
              -4.03e-05,
              -0.0125651,
              -0.042764,
              -0.1137823
            ],
            [
              0.0076679,
              0.006884,
              0.0049718,
              -6e-07,
              -0.0124952,
              -0.0426994,
              -0.1136817
            ],
            [
              0.0075105,
              0.0067245,
              0.0048301,
              -0.0001339,
              -0.0126227,
              -0.0428556,
              -0.1137769
            ],
            [
              0.0072801,
              0.0065373,
              0.0045992,
              -0.0003451,
              -0.0127982,
              -0.0430155,
              -0.1142021
            ],
            [
              0.0071533,
              0.0063774,
              0.0044579,
              -0.000563,
              -0.0129798,
              -0.0432213,
              -0.1143361
            ],
            [
              0.008504,
              0.0075548,
              0.0053358,
              -2.9e-05,
              -0.0128718,
              -0.0432386,
              -0.1141833
            ]
          ]
        },
        "related_pin": "A_N",
        "rise_power power_outputs_1": {
          "index_1": [
            0.01,
            0.0230506,
            0.0531329,
            0.122474,
            0.282311,
            0.650743,
            1.5
          ],
          "index_2": [
            0.0005,
            0.001165835,
            0.002718342,
            0.006338276,
            0.01477877,
            0.03445921,
            0.0803475
          ],
          "values": [
            [
              0.0119118,
              0.0131329,
              0.0155723,
              0.0212822,
              0.0344302,
              0.0647307,
              0.1337283
            ],
            [
              0.0118777,
              0.0130639,
              0.015561,
              0.0213636,
              0.0343347,
              0.0646271,
              0.1345679
            ],
            [
              0.0118952,
              0.0130632,
              0.0155558,
              0.0213,
              0.0343917,
              0.0650372,
              0.1336492
            ],
            [
              0.0117226,
              0.012991,
              0.0155242,
              0.021163,
              0.0343129,
              0.0649089,
              0.133949
            ],
            [
              0.0116755,
              0.0129521,
              0.0155067,
              0.0210918,
              0.0342922,
              0.0648668,
              0.1341232
            ],
            [
              0.0117936,
              0.0128785,
              0.0154976,
              0.0210343,
              0.0344525,
              0.0649454,
              0.1341748
            ],
            [
              0.0119995,
              0.013178,
              0.0157788,
              0.0215142,
              0.0348539,
              0.0650023,
              0.1338552
            ]
          ]
        },
        "when": "(B&C&D)"
      },
      {
        "fall_power power_outputs_1": {
          "index_1": [
            0.01,
            0.0230506,
            0.0531329,
            0.122474,
            0.282311,
            0.650743,
            1.5
          ],
          "index_2": [
            0.0005,
            0.001165835,
            0.002718342,
            0.006338276,
            0.01477877,
            0.03445921,
            0.0803475
          ],
          "values": [
            [
              0.0077259,
              0.0069287,
              0.0049831,
              -5.94e-05,
              -0.0125787,
              -0.0427522,
              -0.1137225
            ],
            [
              0.007735,
              0.006918,
              0.0049941,
              -6.97e-05,
              -0.012564,
              -0.0427497,
              -0.1137091
            ],
            [
              0.0077052,
              0.0068963,
              0.004962,
              -9.78e-05,
              -0.0125877,
              -0.042776,
              -0.1137494
            ],
            [
              0.0075719,
              0.006746,
              0.0047765,
              -0.0002073,
              -0.0127162,
              -0.042918,
              -0.1138644
            ],
            [
              0.0073539,
              0.0065866,
              0.0046352,
              -0.0003684,
              -0.0129186,
              -0.0430906,
              -0.1140331
            ],
            [
              0.0072325,
              0.006397,
              0.004424,
              -0.0006259,
              -0.0131309,
              -0.0433369,
              -0.1141909
            ],
            [
              0.0068344,
              0.0060477,
              0.0040855,
              -0.0009503,
              -0.0134963,
              -0.0437713,
              -0.1145343
            ]
          ]
        },
        "related_pin": "B",
        "rise_power power_outputs_1": {
          "index_1": [
            0.01,
            0.0230506,
            0.0531329,
            0.122474,
            0.282311,
            0.650743,
            1.5
          ],
          "index_2": [
            0.0005,
            0.001165835,
            0.002718342,
            0.006338276,
            0.01477877,
            0.03445921,
            0.0803475
          ],
          "values": [
            [
              0.012138,
              0.0133872,
              0.0158253,
              0.0216417,
              0.0345904,
              0.0647515,
              0.135434
            ],
            [
              0.0121304,
              0.0132872,
              0.0157795,
              0.0215432,
              0.0345049,
              0.0649995,
              0.1330679
            ],
            [
              0.0121297,
              0.0132457,
              0.0158175,
              0.0216163,
              0.0345646,
              0.0650189,
              0.1334871
            ],
            [
              0.0121174,
              0.0132956,
              0.0157641,
              0.0215789,
              0.0345565,
              0.0647817,
              0.1350173
            ],
            [
              0.0119846,
              0.0132071,
              0.0155805,
              0.0213214,
              0.034433,
              0.0650809,
              0.1336209
            ],
            [
              0.0118021,
              0.0129557,
              0.0154592,
              0.0211275,
              0.0343896,
              0.0646362,
              0.134884
            ],
            [
              0.0120414,
              0.0130548,
              0.0155531,
              0.0210272,
              0.0341806,
              0.0642293,
              0.1341867
            ]
          ]
        },
        "when": "(!A_N&C&D)"
      }
    ],
    "max_capacitance": 0.080348,
    "max_transition": 1.497665,
    "power_down_function": "(!VPWR + VGND)",
    "related_ground_pin": "VGND",
    "related_power_pin": "VPWR",
    "timing": [
      {
        "cell_fall del_1_7_7": {
          "index_1": [
            0.01,
            0.0230506,
            0.0531329,
            0.122474,
            0.282311,
            0.650743,
            1.5
          ],
          "index_2": [
            0.0005,
            0.0011658,
            0.0027183,
            0.0063383,
            0.0147788,
            0.0344592,
            0.0803475
          ],
          "values": [
            [
              0.2549528,
              0.2625454,
              0.2769848,
              0.3024886,
              0.3478705,
              0.4346373,
              0.6194266
            ],
            [
              0.2595822,
              0.2672269,
              0.2816725,
              0.3072053,
              0.3523474,
              0.4391358,
              0.6239572
            ],
            [
              0.2705987,
              0.2777712,
              0.2926875,
              0.3178324,
              0.3630461,
              0.4499469,
              0.6345759
            ],
            [
              0.2946607,
              0.302279,
              0.3167999,
              0.3424763,
              0.3881634,
              0.4747146,
              0.6581436
            ],
            [
              0.3425472,
              0.3501577,
              0.3645758,
              0.3903646,
              0.4357565,
              0.5221271,
              0.7072198
            ],
            [
              0.4244482,
              0.4320641,
              0.4465139,
              0.4718868,
              0.5173933,
              0.6040768,
              0.7890042
            ],
            [
              0.5599772,
              0.5676097,
              0.5820603,
              0.6078564,
              0.653171,
              0.740115,
              0.9248119
            ]
          ]
        },
        "cell_rise del_1_7_7": {
          "index_1": [
            0.01,
            0.0230506,
            0.0531329,
            0.122474,
            0.282311,
            0.650743,
            1.5
          ],
          "index_2": [
            0.0005,
            0.0011658,
            0.0027183,
            0.0063383,
            0.0147788,
            0.0344592,
            0.0803475
          ],
          "values": [
            [
              0.3215479,
              0.3327981,
              0.3551967,
              0.3994766,
              0.4891035,
              0.6863669,
              1.1456298
            ],
            [
              0.3251642,
              0.3361749,
              0.358844,
              0.4029047,
              0.4926334,
              0.690393,
              1.145077
            ],
            [
              0.3356762,
              0.3470337,
              0.3695917,
              0.4136898,
              0.5032781,
              0.7006815,
              1.1587658
            ],
            [
              0.3628794,
              0.3739659,
              0.3965567,
              0.4407276,
              0.5304912,
              0.7277675,
              1.1874036
            ],
            [
              0.4277567,
              0.4390588,
              0.4614111,
              0.5055658,
              0.5953312,
              0.7926952,
              1.2526385
            ],
            [
              0.5760538,
              0.5876598,
              0.6100111,
              0.6541453,
              0.7439196,
              0.9414769,
              1.398815
            ],
            [
              0.8615855,
              0.8730174,
              0.8955993,
              0.9397705,
              1.0297245,
              1.2273376,
              1.6842567
            ]
          ]
        },
        "fall_transition del_1_7_7": {
          "index_1": [
            0.01,
            0.0230506,
            0.0531329,
            0.122474,
            0.282311,
            0.650743,
            1.5
          ],
          "index_2": [
            0.0005,
            0.0011658,
            0.0027183,
            0.0063383,
            0.0147788,
            0.0344592,
            0.0803475
          ],
          "values": [
            [
              0.0476304,
              0.0540888,
              0.067079,
              0.0938063,
              0.1503874,
              0.276248,
              0.5859237
            ],
            [
              0.0476125,
              0.0538815,
              0.0669779,
              0.0948916,
              0.1504684,
              0.2762253,
              0.5857515
            ],
            [
              0.0474601,
              0.0538742,
              0.0666916,
              0.0946362,
              0.1503685,
              0.2765292,
              0.5860393
            ],
            [
              0.0472791,
              0.0536231,
              0.0668702,
              0.0930315,
              0.1496584,
              0.2758538,
              0.5864908
            ],
            [
              0.0472598,
              0.0535455,
              0.0665237,
              0.0942987,
              0.1500372,
              0.2762337,
              0.5886892
            ],
            [
              0.0474525,
              0.0539242,
              0.0667063,
              0.0948209,
              0.150453,
              0.2764033,
              0.5872008
            ],
            [
              0.0477049,
              0.0540411,
              0.067037,
              0.0948643,
              0.1504954,
              0.2768969,
              0.5841977
            ]
          ]
        },
        "related_pin": "A_N",
        "rise_transition del_1_7_7": {
          "index_1": [
            0.01,
            0.0230506,
            0.0531329,
            0.122474,
            0.282311,
            0.650743,
            1.5
          ],
          "index_2": [
            0.0005,
            0.0011658,
            0.0027183,
            0.0063383,
            0.0147788,
            0.0344592,
            0.0803475
          ],
          "values": [
            [
              0.0653163,
              0.078499,
              0.1065548,
              0.1680181,
              0.3112531,
              0.6613379,
              1.4874451
            ],
            [
              0.0654603,
              0.0788251,
              0.1067665,
              0.167657,
              0.3112712,
              0.6601325,
              1.4925732
            ],
            [
              0.0649026,
              0.0786968,
              0.1065365,
              0.1680502,
              0.3119409,
              0.6595133,
              1.483618
            ],
            [
              0.0656859,
              0.0788222,
              0.1062843,
              0.1679171,
              0.3120774,
              0.6613976,
              1.4958411
            ],
            [
              0.0654239,
              0.0785684,
              0.1065681,
              0.1679021,
              0.3120581,
              0.6614124,
              1.4968819
            ],
            [
              0.0654895,
              0.0784961,
              0.1067478,
              0.1678208,
              0.3119356,
              0.6605154,
              1.4974545
            ],
            [
              0.0665133,
              0.0791713,
              0.1067915,
              0.1678544,
              0.3120631,
              0.661129,
              1.4815195
            ]
          ]
        },
        "sdf_cond": "B==1'b1&&C==1'b1&&D==1'b1",
        "timing_sense": "negative_unate",
        "timing_type": "combinational",
        "when": "(B&C&D)"
      },
      {
        "cell_fall del_1_7_7": {
          "index_1": [
            0.01,
            0.0230506,
            0.0531329,
            0.122474,
            0.282311,
            0.650743,
            1.5
          ],
          "index_2": [
            0.0005,
            0.0011658,
            0.0027183,
            0.0063383,
            0.0147788,
            0.0344592,
            0.0803475
          ],
          "values": [
            [
              0.238318,
              0.2458312,
              0.2603776,
              0.286135,
              0.3318018,
              0.4187837,
              0.603829
            ],
            [
              0.2433556,
              0.2508689,
              0.2654372,
              0.2912721,
              0.3368957,
              0.423875,
              0.6090071
            ],
            [
              0.2546168,
              0.26224,
              0.2766514,
              0.3024675,
              0.3481393,
              0.4351253,
              0.6202556
            ],
            [
              0.2822774,
              0.2898281,
              0.3042837,
              0.3301067,
              0.3759887,
              0.4628754,
              0.6481646
            ],
            [
              0.3468452,
              0.3544881,
              0.3688764,
              0.3947019,
              0.4404349,
              0.5274703,
              0.7126024
            ],
            [
              0.5038339,
              0.5114742,
              0.5258368,
              0.5515039,
              0.5973584,
              0.6843128,
              0.8696649
            ],
            [
              0.849022,
              0.8574958,
              0.8733668,
              0.9012203,
              0.9483625,
              1.0366261,
              1.2223806
            ]
          ]
        },
        "cell_rise del_1_7_7": {
          "index_1": [
            0.01,
            0.0230506,
            0.0531329,
            0.122474,
            0.282311,
            0.650743,
            1.5
          ],
          "index_2": [
            0.0005,
            0.0011658,
            0.0027183,
            0.0063383,
            0.0147788,
            0.0344592,
            0.0803475
          ],
          "values": [
            [
              0.2116481,
              0.2233112,
              0.2456315,
              0.2896161,
              0.3791918,
              0.5763256,
              1.031694
            ],
            [
              0.2156037,
              0.2268379,
              0.2492672,
              0.293528,
              0.3830137,
              0.5799705,
              1.0369404
            ],
            [
              0.2248558,
              0.2360489,
              0.2587408,
              0.3026765,
              0.3922035,
              0.5890455,
              1.046967
            ],
            [
              0.2441648,
              0.2554274,
              0.2779399,
              0.3219539,
              0.4115843,
              0.6089749,
              1.0638398
            ],
            [
              0.2885084,
              0.299836,
              0.3222569,
              0.3664011,
              0.455826,
              0.6532953,
              1.1100588
            ],
            [
              0.3846953,
              0.3962855,
              0.4203614,
              0.4649049,
              0.5547206,
              0.7521188,
              1.2088373
            ],
            [
              0.5581759,
              0.5706985,
              0.5956496,
              0.6421988,
              0.73413,
              0.9335653,
              1.3903416
            ]
          ]
        },
        "fall_transition del_1_7_7": {
          "index_1": [
            0.01,
            0.0230506,
            0.0531329,
            0.122474,
            0.282311,
            0.650743,
            1.5
          ],
          "index_2": [
            0.0005,
            0.0011658,
            0.0027183,
            0.0063383,
            0.0147788,
            0.0344592,
            0.0803475
          ],
          "values": [
            [
              0.048175,
              0.0548148,
              0.0677126,
              0.0945478,
              0.1504229,
              0.2766921,
              0.5871542
            ],
            [
              0.048182,
              0.0548328,
              0.0677018,
              0.0945369,
              0.1503059,
              0.2769866,
              0.5876631
            ],
            [
              0.0481556,
              0.0545141,
              0.0677386,
              0.0944989,
              0.1503405,
              0.2768988,
              0.5872191
            ],
            [
              0.0482567,
              0.0547543,
              0.067555,
              0.0937937,
              0.1506483,
              0.2768976,
              0.5902161
            ],
            [
              0.0488571,
              0.0555582,
              0.0679241,
              0.0953274,
              0.150111,
              0.2770319,
              0.5865534
            ],
            [
              0.0481366,
              0.0545215,
              0.0683107,
              0.0937726,
              0.1507096,
              0.2767938,
              0.5887932
            ],
            [
              0.0584582,
              0.0653483,
              0.0775556,
              0.102925,
              0.1566941,
              0.2801706,
              0.5883947
            ]
          ]
        },
        "related_pin": "B",
        "rise_transition del_1_7_7": {
          "index_1": [
            0.01,
            0.0230506,
            0.0531329,
            0.122474,
            0.282311,
            0.650743,
            1.5
          ],
          "index_2": [
            0.0005,
            0.0011658,
            0.0027183,
            0.0063383,
            0.0147788,
            0.0344592,
            0.0803475
          ],
          "values": [
            [
              0.0652053,
              0.0782943,
              0.1066192,
              0.1677489,
              0.3117779,
              0.6595292,
              1.4946043
            ],
            [
              0.0649312,
              0.0789212,
              0.1067624,
              0.1681423,
              0.3119529,
              0.6586308,
              1.4823969
            ],
            [
              0.0653311,
              0.0789961,
              0.1065958,
              0.168128,
              0.3116178,
              0.6615642,
              1.486619
            ],
            [
              0.0660294,
              0.0785976,
              0.1066767,
              0.1678417,
              0.3113931,
              0.6593894,
              1.4944794
            ],
            [
              0.0659572,
              0.0784025,
              0.1064141,
              0.1679279,
              0.3117869,
              0.6602793,
              1.4823039
            ],
            [
              0.0680195,
              0.0811348,
              0.1086138,
              0.1699325,
              0.312681,
              0.6616102,
              1.4976648
            ],
            [
              0.078259,
              0.0916381,
              0.1186934,
              0.1780328,
              0.3190237,
              0.6622014,
              1.4899929
            ]
          ]
        },
        "sdf_cond": "AN==1'b0&&C==1'b1&&D==1'b1",
        "timing_sense": "positive_unate",
        "timing_type": "combinational",
        "when": "(!A_N&C&D)"
      },
      {
        "cell_fall del_1_7_7": {
          "index_1": [
            0.01,
            0.0230506,
            0.0531329,
            0.122474,
            0.282311,
            0.650743,
            1.5
          ],
          "index_2": [
            0.0005,
            0.0011658,
            0.0027183,
            0.0063383,
            0.0147788,
            0.0344592,
            0.0803475
          ],
          "values": [
            [
              0.2592193,
              0.2672818,
              0.2818638,
              0.3077096,
              0.353894,
              0.4415502,
              0.6272486
            ],
            [
              0.2641392,
              0.2718428,
              0.2861862,
              0.3123181,
              0.3587587,
              0.4460601,
              0.6317811
            ],
            [
              0.2751366,
              0.2828836,
              0.2975414,
              0.3233745,
              0.3698011,
              0.4571649,
              0.6429831
            ],
            [
              0.3026877,
              0.3103937,
              0.3249719,
              0.3511782,
              0.3972093,
              0.4846681,
              0.6704242
            ],
            [
              0.3697203,
              0.3774572,
              0.392075,
              0.4182437,
              0.4643193,
              0.5517786,
              0.7376302
            ],
            [
              0.5241075,
              0.5318021,
              0.5464473,
              0.5723146,
              0.6183676,
              0.7060285,
              0.8919302
            ],
            [
              0.8796507,
              0.8880122,
              0.9034877,
              0.9306752,
              0.9773728,
              1.0648258,
              1.2508854
            ]
          ]
        },
        "cell_rise del_1_7_7": {
          "index_1": [
            0.01,
            0.0230506,
            0.0531329,
            0.122474,
            0.282311,
            0.650743,
            1.5
          ],
          "index_2": [
            0.0005,
            0.0011658,
            0.0027183,
            0.0063383,
            0.0147788,
            0.0344592,
            0.0803475
          ],
          "values": [
            [
              0.2198767,
              0.2311322,
              0.2536264,
              0.2977379,
              0.3872334,
              0.5840032,
              1.0394463
            ],
            [
              0.2240583,
              0.2352956,
              0.2579235,
              0.3019723,
              0.3913319,
              0.587996,
              1.0445276
            ],
            [
              0.2333814,
              0.2446866,
              0.2673635,
              0.3113557,
              0.4008612,
              0.5975811,
              1.0560348
            ],
            [
              0.2526193,
              0.2638835,
              0.2863959,
              0.3305343,
              0.4199089,
              0.6169488,
              1.0714543
            ],
            [
              0.2922053,
              0.3035021,
              0.3260753,
              0.3700713,
              0.4596008,
              0.6566693,
              1.1121969
            ],
            [
              0.3783144,
              0.3900028,
              0.4131202,
              0.4576712,
              0.5475703,
              0.7450747,
              1.1994765
            ],
            [
              0.5401538,
              0.553029,
              0.5779889,
              0.6247051,
              0.7165015,
              0.9151296,
              1.3719401
            ]
          ]
        },
        "fall_transition del_1_7_7": {
          "index_1": [
            0.01,
            0.0230506,
            0.0531329,
            0.122474,
            0.282311,
            0.650743,
            1.5
          ],
          "index_2": [
            0.0005,
            0.0011658,
            0.0027183,
            0.0063383,
            0.0147788,
            0.0344592,
            0.0803475
          ],
          "values": [
            [
              0.0505631,
              0.0556134,
              0.0694256,
              0.0958483,
              0.1517766,
              0.2787624,
              0.5892031
            ],
            [
              0.0491942,
              0.0556203,
              0.069046,
              0.0954964,
              0.1519215,
              0.2781192,
              0.5889589
            ],
            [
              0.0498658,
              0.0568404,
              0.0693323,
              0.0954724,
              0.1519174,
              0.2776649,
              0.5886974
            ],
            [
              0.0505531,
              0.0570252,
              0.0695253,
              0.0965838,
              0.1514962,
              0.2783599,
              0.5869498
            ],
            [
              0.050266,
              0.0568957,
              0.069685,
              0.0950363,
              0.1518017,
              0.2781995,
              0.5890927
            ],
            [
              0.0492589,
              0.0556998,
              0.068772,
              0.0966922,
              0.1515526,
              0.2783105,
              0.5907625
            ],
            [
              0.0565009,
              0.0627183,
              0.0753645,
              0.1005083,
              0.1548437,
              0.2801776,
              0.5884098
            ]
          ]
        },
        "related_pin": "C",
        "rise_transition del_1_7_7": {
          "index_1": [
            0.01,
            0.0230506,
            0.0531329,
            0.122474,
            0.282311,
            0.650743,
            1.5
          ],
          "index_2": [
            0.0005,
            0.0011658,
            0.0027183,
            0.0063383,
            0.0147788,
            0.0344592,
            0.0803475
          ],
          "values": [
            [
              0.065627,
              0.0788134,
              0.1062222,
              0.1674975,
              0.3118647,
              0.6603324,
              1.4964233
            ],
            [
              0.0652624,
              0.0787669,
              0.1067294,
              0.1681737,
              0.3120114,
              0.6589059,
              1.4845235
            ],
            [
              0.0655555,
              0.0789727,
              0.106745,
              0.1677763,
              0.3114673,
              0.661176,
              1.494817
            ],
            [
              0.065653,
              0.0787153,
              0.1066631,
              0.1679811,
              0.311406,
              0.6603695,
              1.4920608
            ],
            [
              0.064996,
              0.0786343,
              0.1060134,
              0.1676235,
              0.312135,
              0.6611442,
              1.4868564
            ],
            [
              0.0687257,
              0.0807691,
              0.1088925,
              0.1698554,
              0.3121419,
              0.6606399,
              1.4835497
            ],
            [
              0.0761067,
              0.088706,
              0.1168987,
              0.1768711,
              0.318155,
              0.6606049,
              1.4893936
            ]
          ]
        },
        "sdf_cond": "AN==1'b0&&B==1'b1&&D==1'b1",
        "timing_sense": "positive_unate",
        "timing_type": "combinational",
        "when": "(!A_N&B&D)"
      },
      {
        "cell_fall del_1_7_7": {
          "index_1": [
            0.01,
            0.0230506,
            0.0531329,
            0.122474,
            0.282311,
            0.650743,
            1.5
          ],
          "index_2": [
            0.0005,
            0.0011658,
            0.0027183,
            0.0063383,
            0.0147788,
            0.0344592,
            0.0803475
          ],
          "values": [
            [
              0.2849486,
              0.292838,
              0.3076358,
              0.3337394,
              0.3802332,
              0.4681149,
              0.6544853
            ],
            [
              0.2890657,
              0.2968855,
              0.3116617,
              0.337806,
              0.3841464,
              0.4719905,
              0.6584571
            ],
            [
              0.3003484,
              0.3082166,
              0.3230693,
              0.3488947,
              0.3958414,
              0.483565,
              0.6698867
            ],
            [
              0.327403,
              0.335289,
              0.3501401,
              0.3761948,
              0.4229792,
              0.5108577,
              0.6971442
            ],
            [
              0.3933185,
              0.401174,
              0.4160091,
              0.4424682,
              0.4889685,
              0.5769918,
              0.763464
            ],
            [
              0.5462936,
              0.5542141,
              0.5691365,
              0.5955176,
              0.6420511,
              0.7299958,
              0.916305
            ],
            [
              0.9053724,
              0.9136067,
              0.928866,
              0.9556762,
              1.0029499,
              1.0914477,
              1.2778421
            ]
          ]
        },
        "cell_rise del_1_7_7": {
          "index_1": [
            0.01,
            0.0230506,
            0.0531329,
            0.122474,
            0.282311,
            0.650743,
            1.5
          ],
          "index_2": [
            0.0005,
            0.0011658,
            0.0027183,
            0.0063383,
            0.0147788,
            0.0344592,
            0.0803475
          ],
          "values": [
            [
              0.2299397,
              0.2411552,
              0.2637041,
              0.3078903,
              0.3973785,
              0.5937137,
              1.0504475
            ],
            [
              0.2344677,
              0.2456102,
              0.2684161,
              0.3124131,
              0.4018802,
              0.5984118,
              1.0525992
            ],
            [
              0.2437567,
              0.2552957,
              0.2775536,
              0.3217612,
              0.4111841,
              0.607583,
              1.0643637
            ],
            [
              0.2626824,
              0.2739408,
              0.2964419,
              0.3405405,
              0.4300442,
              0.6266304,
              1.0814944
            ],
            [
              0.3005106,
              0.3117567,
              0.33436,
              0.3783321,
              0.4676376,
              0.6639616,
              1.1217522
            ],
            [
              0.3785449,
              0.3901595,
              0.4131654,
              0.4576431,
              0.5475863,
              0.7447764,
              1.199019
            ],
            [
              0.5250625,
              0.5382239,
              0.5628797,
              0.6092687,
              0.7015494,
              0.9001938,
              1.3558561
            ]
          ]
        },
        "fall_transition del_1_7_7": {
          "index_1": [
            0.01,
            0.0230506,
            0.0531329,
            0.122474,
            0.282311,
            0.650743,
            1.5
          ],
          "index_2": [
            0.0005,
            0.0011658,
            0.0027183,
            0.0063383,
            0.0147788,
            0.0344592,
            0.0803475
          ],
          "values": [
            [
              0.0510204,
              0.0575715,
              0.0708292,
              0.0993394,
              0.1548939,
              0.2813369,
              0.5919427
            ],
            [
              0.0517748,
              0.0576289,
              0.0708815,
              0.0994457,
              0.1552737,
              0.2811448,
              0.5919967
            ],
            [
              0.0510284,
              0.0575704,
              0.0708695,
              0.0984315,
              0.1549044,
              0.2808605,
              0.5907457
            ],
            [
              0.0511491,
              0.057621,
              0.0720979,
              0.0982403,
              0.1546008,
              0.281297,
              0.5905602
            ],
            [
              0.0525536,
              0.0592688,
              0.0722313,
              0.0994122,
              0.1547923,
              0.2808126,
              0.5919457
            ],
            [
              0.0510484,
              0.0575142,
              0.0722461,
              0.0980233,
              0.1546879,
              0.281315,
              0.5912155
            ],
            [
              0.0557964,
              0.0624122,
              0.0750104,
              0.1015495,
              0.1566455,
              0.2826998,
              0.5912634
            ]
          ]
        },
        "related_pin": "D",
        "rise_transition del_1_7_7": {
          "index_1": [
            0.01,
            0.0230506,
            0.0531329,
            0.122474,
            0.282311,
            0.650743,
            1.5
          ],
          "index_2": [
            0.0005,
            0.0011658,
            0.0027183,
            0.0063383,
            0.0147788,
            0.0344592,
            0.0803475
          ],
          "values": [
            [
              0.065696,
              0.078883,
              0.1063708,
              0.1676759,
              0.311938,
              0.6613933,
              1.4954867
            ],
            [
              0.0661781,
              0.0789719,
              0.1067292,
              0.1678602,
              0.3116372,
              0.6590804,
              1.4949822
            ],
            [
              0.0655797,
              0.0783168,
              0.1067782,
              0.1678244,
              0.3112517,
              0.6616513,
              1.4948799
            ],
            [
              0.0656154,
              0.0787957,
              0.106674,
              0.1675661,
              0.3118863,
              0.6601223,
              1.4965433
            ],
            [
              0.0652021,
              0.0785789,
              0.1064801,
              0.1680338,
              0.3115472,
              0.661028,
              1.485427
            ],
            [
              0.0681584,
              0.0804468,
              0.1084622,
              0.1700343,
              0.3127076,
              0.66032,
              1.4895467
            ],
            [
              0.0754261,
              0.0873958,
              0.1167657,
              0.1779633,
              0.3180546,
              0.6604367,
              1.4917537
            ]
          ]
        },
        "sdf_cond": "AN==1'b0&&B==1'b1&&C==1'b1",
        "timing_sense": "positive_unate",
        "timing_type": "combinational",
        "when": "(!A_N&B&C)"
      }
    ]
  }
}